Lab 10/design.sv
module counter_fsm
(
	input  clock, x, reset,
	output reg z
);
	
  reg[1:0] state;
  
  parameter S0 = 0, S1 = 1, S2 = 2, S3 = 3;
  
  
  always @(state) begin
    case (state)
      S0:
        z = 1'b0;
      S1:
        z = 1'b1;
      S2:
        z = 1'b0;
      S3:
        z = 1'b1;
      default:
        z = 1'b0;
    endcase
  end
  
  always @(posedge clock) begin
    if (reset)
      state <= S0;
    else
      case(state)
        S0:
          if (x) state <= S3;
          else state <= S1;
        S1:
          if (x) state <= S0;
          else state <= S2;
        S2:
          if (x) state <= S1;
        else state <= S3;
        S3:
          if (x) state <= S2;
          else state <= S0;
      endcase
  end

	
endmodule

Lab 10/testbench.sv
module counter_fsm_tb;

	reg  CLOCK, X, RESET;
	wire Z;

  	counter_fsm DUT( .clock(CLOCK), .x(X), .reset(RESET), .z(Z));

	
    always #10 CLOCK = ~CLOCK;                   
                       
    initial
	begin
		$dumpfile("dump.vcd"); $dumpvars;
   	
     	CLOCK = 1;
   		RESET = 1;	
   			
   		#10 RESET = 0;
		
      $display("DOWN COUNTING","\n");
 		#10 X = 1;
      $display("STATE = ", DUT.state, " INPUT = ", X, ", OUTPUT = ", Z);
      
      	#20 $display("STATE = ", DUT.state, " INPUT = ", X, ", OUTPUT = ", Z);
      
      	#20 $display("STATE = ", DUT.state, " INPUT = ", X, ", OUTPUT = ", Z);
      
        #20 $display("STATE = ", DUT.state, " INPUT = ", X, ", OUTPUT = ", Z, "\n");
      
      $display("UP COUNTING","\n");
      	#140 X = 0;
      	$display("STATE = ", DUT.state, " INPUT = ", X, ", OUTPUT = ", Z);
      
      	#20 $display("STATE = ", DUT.state, " INPUT = ", X, ", OUTPUT = ", Z);
      
      	#20 $display("STATE = ", DUT.state, " INPUT = ", X, ", OUTPUT = ", Z);
      
      	#20 $display("STATE = ", DUT.state, " INPUT = ", X, ", OUTPUT = ", Z);
     	
      	#80 X = 1;

		#300 $finish;
	end
        


endmodule

Lab 10/dump.vcd
$date
    Oct 14, 2021  03:52:54
$end
$version
    TOOL:	xmsim	20.09-s003
$end
$timescale
    1 ns
$end

$scope module counter_fsm_tb $end
$var reg       1 !    CLOCK $end
$var reg       1 "    X $end
$var reg       1 #    RESET $end
$var wire      1 $    Z  $end

$scope module DUT $end
$var wire      1 %    clock  $end
$var wire      1 &    x  $end
$var wire      1 '    reset  $end
$var reg       1 (    z $end
$var reg       2 )    state [1:0] $end
$var parameter 32 *    S0 $end
$var parameter 32 +    S1 $end
$var parameter 32 ,    S2 $end
$var parameter 32 -    S3 $end
$upscope $end

$upscope $end

$enddefinitions $end
$dumpvars
b11 -
b10 ,
b1 +
b0 *
1!
x"
1#
0$
1%
x&
1'
0(
b0 )
$end
#10
0!
0#
0'
0%
#20
1!
1"
1&
1%
b11 )
1(
1$
#30
0!
0%
#40
1!
1%
b10 )
0(
0$
#50
0!
0%
#60
1!
1%
b1 )
1(
1$
#70
0!
0%
#80
1!
1%
b0 )
0(
0$
#90
0!
0%
#100
1!
1%
b11 )
1(
1$
#110
0!
0%
#120
1!
1%
b10 )
0(
0$
#130
0!
0%
#140
1!
1%
b1 )
1(
1$
#150
0!
0%
#160
1!
1%
b0 )
0(
0$
#170
0!
0%
#180
1!
1%
b11 )
1(
1$
#190
0!
0%
#200
1!
1%
b10 )
0(
0$
#210
0!
0%
#220
0"
1!
1%
0&
b11 )
1(
1$
#230
0!
0%
#240
1!
1%
b0 )
0(
0$
#250
0!
0%
#260
1!
1%
b1 )
1(
1$
#270
0!
0%
#280
1!
1%
b10 )
0(
0$
#290
0!
0%
#300
1!
1%
b11 )
1(
1$
#310
0!
0%
#320
1!
1%
b0 )
0(
0$
#330
0!
0%
#340
1!
1%
b1 )
1(
1$
#350
0!
0%
#360
1"
1!
1%
1&
b0 )
0(
0$
#370
0!
0%
#380
1!
1%
b11 )
1(
1$
#390
0!
0%
#400
1!
1%
b10 )
0(
0$
#410
0!
0%
#420
1!
1%
b1 )
1(
1$
#430
0!
0%
#440
1!
1%
b0 )
0(
0$
#450
0!
0%
#460
1!
1%
b11 )
1(
1$
#470
0!
0%
#480
1!
1%
b10 )
0(
0$
#490
0!
0%
#500
1!
1%
b1 )
1(
1$
#510
0!
0%
#520
1!
1%
b0 )
0(
0$
#530
0!
0%
#540
1!
1%
b11 )
1(
1$
#550
0!
0%
#560
1!
1%
b10 )
0(
0$
#570
0!
0%
#580
1!
1%
b1 )
1(
1$
#590
0!
0%
#600
1!
1%
b0 )
0(
0$
#610
0!
0%
#620
1!
1%
b11 )
1(
1$
#630
0!
0%
#640
1!
1%
b10 )
0(
0$
